ttk_custom_msgbox/__init__.py
ttk_custom_msgbox/custom.png
ttk_custom_msgbox/error.png
ttk_custom_msgbox/example.png
ttk_custom_msgbox/example.py
ttk_custom_msgbox/info.png
ttk_custom_msgbox/ttk_custom_msgbox.py
ttk_custom_msgbox/warning.png
ttk_custom_msgbox-0.0.7.dist-info/LICENSE
ttk_custom_msgbox-0.0.7.dist-info/METADATA
ttk_custom_msgbox-0.0.7.dist-info/WHEEL
ttk_custom_msgbox-0.0.7.dist-info/top_level.txt
ttk_custom_msgbox-0.0.7.dist-info/RECORD
