Metadata-Version: 2.1
Name: ttk-custom-msgbox
Version: 0.0.7
Summary: A simple customizable messagebox for themed tkinter (ttk). Includes 3 built in messagebox types.
Home-page: https://github.com/robertitoss1/ttk-custom-msgbox
Author: Robert Salamon
Project-URL: Bug Tracker, https://github.com/robertitoss1/ttk-custom-msgbox
Classifier: Programming Language :: Python :: 3.10
Classifier: License :: OSI Approved :: MIT License
Classifier: Operating System :: Microsoft :: Windows :: Windows 10
Requires-Python: >=3.10
License-File: LICENSE
